fastapi_translations/__init__.py
fastapi_translations/cli.py
fastapi_translations/git.py
fastapi_translations/printer.py
fastapi_translations/version.py
fastapi_translations/translations/__init__.py
fastapi_translations/translations/document.py
fastapi_translations/translations/languages.py
fastapi_translations/translations/summary.py
fastapi_translations-0.0.9.dist-info/METADATA
fastapi_translations-0.0.9.dist-info/WHEEL
fastapi_translations-0.0.9.dist-info/entry_points.txt
fastapi_translations-0.0.9.dist-info/licenses/LICENSE
fastapi_translations-0.0.9.dist-info/RECORD
